MANIFEST.in
README.txt
setup.py
emogenerator/__init__.py
emogenerator/emogenerator.py
emogenerator.egg-info/PKG-INFO
emogenerator.egg-info/SOURCES.txt
emogenerator.egg-info/dependency_links.txt
emogenerator.egg-info/requires.txt
emogenerator.egg-info/top_level.txt
emogenerator.egg-info/zip-safe
emogenerator/templates/_defaults.plist
emogenerator/templates/attribute.h.genshi
emogenerator/templates/attribute.m.genshi
emogenerator/templates/classname.h.genshi
emogenerator/templates/classname.m.genshi
emogenerator/templates/relationship.h.genshi
emogenerator/templates/relationship.m.genshi
emogenerator/templates/relationship_methods.h.genshi
scripts/emogenerator