Metadata-Version: 1.0
Name: emogenerator
Version: 0.1.13
Summary: Estranged Managed Object Generator
Home-page: http://github.com/schwa/emogenerator
Author: Jonathan Wight
Author-email: jwight@mac.com
License: BSD License
Platform: UNKNOWN
Classifier: Development Status :: 3 - Alpha
Classifier: Environment :: MacOS X :: Cocoa
Classifier: Intended Audience :: Developers
Classifier: License :: OSI Approved :: BSD License
Classifier: Operating System :: MacOS :: MacOS X
Classifier: Programming Language :: Objective C
Classifier: Topic :: Database
Classifier: Topic :: Software Development :: Build Tools
